miiflow_llm/__init__.py
miiflow_llm/core/__init__.py
miiflow_llm/core/agent.py
miiflow_llm/core/callback_context.py
miiflow_llm/core/callbacks.py
miiflow_llm/core/client.py
miiflow_llm/core/exceptions.py
miiflow_llm/core/message.py
miiflow_llm/core/metrics.py
miiflow_llm/core/observability/__init__.py
miiflow_llm/core/observability/auto_instrumentation.py
miiflow_llm/core/observability/config.py
miiflow_llm/core/observability/context.py
miiflow_llm/core/observability/logging.py
miiflow_llm/core/react/__init__.py
miiflow_llm/core/react/enums.py
miiflow_llm/core/react/events/__init__.py
miiflow_llm/core/react/events/agui_factory.py
miiflow_llm/core/react/events/bus.py
miiflow_llm/core/react/events/formatters.py
miiflow_llm/core/react/exceptions.py
miiflow_llm/core/react/execution/__init__.py
miiflow_llm/core/react/execution/state.py
miiflow_llm/core/react/factory.py
miiflow_llm/core/react/models.py
miiflow_llm/core/react/multi_agent_orchestrator.py
miiflow_llm/core/react/orchestrator.py
miiflow_llm/core/react/parallel_plan_orchestrator.py
miiflow_llm/core/react/parser.py
miiflow_llm/core/react/parsing/__init__.py
miiflow_llm/core/react/parsing/strategies/__init__.py
miiflow_llm/core/react/parsing/xml_parser.py
miiflow_llm/core/react/plan_execute_orchestrator.py
miiflow_llm/core/react/prompts.py
miiflow_llm/core/react/react_events.py
miiflow_llm/core/react/safety.py
miiflow_llm/core/react/shared_state.py
miiflow_llm/core/react/tool_executor.py
miiflow_llm/core/schema_normalizer.py
miiflow_llm/core/stream_normalizer.py
miiflow_llm/core/streaming.py
miiflow_llm/core/tools/__init__.py
miiflow_llm/core/tools/decorators.py
miiflow_llm/core/tools/exceptions.py
miiflow_llm/core/tools/function/__init__.py
miiflow_llm/core/tools/function/context_patterns.py
miiflow_llm/core/tools/function/function_tool.py
miiflow_llm/core/tools/http/__init__.py
miiflow_llm/core/tools/http/http_tool.py
miiflow_llm/core/tools/http/proxy_utils.py
miiflow_llm/core/tools/mcp/__init__.py
miiflow_llm-0.4.0.dist-info/METADATA
miiflow_llm-0.4.0.dist-info/WHEEL
miiflow_llm-0.4.0.dist-info/licenses/LICENSE
miiflow_llm-0.4.0.dist-info/RECORD
