Metadata-Version: 2.4
Name: miiflow-llm
Version: 0.4.0
Summary: A lightweight, unified interface for LLM providers with streaming, tool calling, and structured output support
License: MIT
License-File: LICENSE
Keywords: llm,openai,anthropic,agents,streaming,tools
Author: Yaozhong Kang
Author-email: yaozhong@miiflow.ai
Maintainer: Yaozhong Kang
Maintainer-email: yaozhong@miiflow.ai
Requires-Python: >=3.9,<3.13
Classifier: Development Status :: 4 - Beta
Classifier: Intended Audience :: Developers
Classifier: License :: OSI Approved :: MIT License
Classifier: Programming Language :: Python :: 3
Classifier: Programming Language :: Python :: 3.9
Classifier: Programming Language :: Python :: 3.10
Classifier: Programming Language :: Python :: 3.11
Classifier: Programming Language :: Python :: 3.12
Classifier: Topic :: Scientific/Engineering :: Artificial Intelligence
Classifier: Topic :: Software Development :: Libraries :: Python Modules
Provides-Extra: agui
Provides-Extra: all
Provides-Extra: examples
Provides-Extra: google
Provides-Extra: groq
Provides-Extra: mcp
Provides-Extra: mistral
Provides-Extra: multimedia
Provides-Extra: observability
Provides-Extra: pdf
Requires-Dist: PyMuPDF (>=1.23.0,<2.0.0) ; extra == "pdf" or extra == "multimedia" or extra == "all"
Requires-Dist: ag-ui-protocol (>=0.1.10,<0.2.0) ; extra == "agui" or extra == "all"
Requires-Dist: aiohttp (>=3.9.0,<4.0.0)
Requires-Dist: anthropic (>=0.74.0,<0.75.0)
Requires-Dist: arize-phoenix (>=4.29.0,<5.0.0) ; extra == "observability" or extra == "all"
Requires-Dist: google-generativeai (>=0.8.0,<0.9.0) ; extra == "google" or extra == "all"
Requires-Dist: groq (>=0.13.0,<0.14.0) ; extra == "groq" or extra == "all"
Requires-Dist: httpx (>=0.28.0,<0.29.0)
Requires-Dist: mcp (>=1.0.0,<2.0.0) ; (python_version >= "3.10") and (extra == "mcp" or extra == "all")
Requires-Dist: mistralai (>=1.0.0,<2.0.0) ; extra == "mistral" or extra == "all"
Requires-Dist: openai (>=1.50.0,<2.0.0)
Requires-Dist: openinference-instrumentation-anthropic (>=0.1.5,<0.2.0) ; extra == "observability" or extra == "all"
Requires-Dist: openinference-instrumentation-google-genai (>=0.1.0,<0.2.0) ; extra == "observability" or extra == "all"
Requires-Dist: openinference-instrumentation-openai (>=0.1.12,<0.2.0) ; extra == "observability" or extra == "all"
Requires-Dist: opentelemetry-api (>=1.27.0,<2.0.0) ; extra == "observability" or extra == "all"
Requires-Dist: opentelemetry-exporter-otlp (>=1.27.0,<2.0.0) ; extra == "observability" or extra == "all"
Requires-Dist: opentelemetry-sdk (>=1.27.0,<2.0.0) ; extra == "observability" or extra == "all"
Requires-Dist: prometheus-client (>=0.21.0,<0.22.0) ; extra == "observability" or extra == "all"
Requires-Dist: pydantic (>=2.0.0,<3.0.0)
Requires-Dist: structlog (>=25.3.0,<26.0.0)
Requires-Dist: tenacity (>=9.0.0,<10.0.0)
Requires-Dist: tiktoken (>=0.8.0,<0.9.0)
Requires-Dist: typing-extensions (>=4.8.0,<5.0.0)
Requires-Dist: yfinance (>=0.2.40,<0.3.0) ; extra == "examples" or extra == "all"
Project-URL: Documentation, https://github.com/Miiflow/miiflow-llm#readme
Project-URL: Homepage, https://github.com/Miiflow/miiflow-llm
Project-URL: Repository, https://github.com/Miiflow/miiflow-llm
